aasms/__init__.py
aasms/aasms.py
aasms/send-aa-sms.py
aasms-0.9.dist-info/COPYING
aasms-0.9.dist-info/METADATA
aasms-0.9.dist-info/WHEEL
aasms-0.9.dist-info/entry_points.txt
aasms-0.9.dist-info/RECORD
